<annotation>
	<folder>images</folder>
	<filename>00135.jpg</filename>
	<path>/home/erb/ufsc/ine5448/PalmALNet/CROI/data/palmprint/images/00135.jpg</path>
	<source>
		<database>Unknown</database>
	</source>
	<size>
		<width>360</width>
		<height>640</height>
		<depth>3</depth>
	</size>
	<segmented>0</segmented>
	<object>
		<name>palm</name>
		<pose>Unspecified</pose>
		<truncated>0</truncated>
		<difficult>0</difficult>
		<robndbox>
			<cx>184.2421</cx>
			<cy>419.6013</cy>
			<w>129.2374</w>
			<h>159.6582</h>
			<angle>2.171593</angle>
		</robndbox>
		<extra/>
	</object>
	<object>
		<name>left_hand</name>
		<pose>Unspecified</pose>
		<truncated>0</truncated>
		<difficult>0</difficult>
		<robndbox>
			<cx>195.3633</cx>
			<cy>377.777</cy>
			<w>301.0</w>
			<h>326.0</h>
			<angle>0.0</angle>
		</robndbox>
		<extra/>
	</object>
</annotation>
