<annotation>
	<folder>images</folder>
	<filename>00220.jpg</filename>
	<path>/home/erb/ufsc/ine5448/PalmALNet/CROI/data/palmprint/images/00220.jpg</path>
	<source>
		<database>Unknown</database>
	</source>
	<size>
		<width>360</width>
		<height>640</height>
		<depth>3</depth>
	</size>
	<segmented>0</segmented>
	<object>
		<name>palm</name>
		<pose>Unspecified</pose>
		<truncated>0</truncated>
		<difficult>0</difficult>
		<robndbox>
			<cx>218.8633</cx>
			<cy>389.777</cy>
			<w>157.5869</w>
			<h>163.482</h>
			<angle>5.613185</angle>
		</robndbox>
		<extra/>
	</object>
	<object>
		<name>right_hand</name>
		<pose>Unspecified</pose>
		<truncated>0</truncated>
		<difficult>0</difficult>
		<robndbox>
			<cx>205.4317</cx>
			<cy>353.1986</cy>
			<w>309.1367</w>
			<h>342.8432</h>
			<angle>0.0</angle>
		</robndbox>
		<extra/>
	</object>
</annotation>
